main/__init__.py
main/args.py
main/csv.py
main/main.py
main/ocr.py
main/tokenizer.py
manga_wordlist_extractor-0.2.1.dist-info/LICENSE
manga_wordlist_extractor-0.2.1.dist-info/METADATA
manga_wordlist_extractor-0.2.1.dist-info/WHEEL
manga_wordlist_extractor-0.2.1.dist-info/entry_points.txt
manga_wordlist_extractor-0.2.1.dist-info/top_level.txt
manga_wordlist_extractor-0.2.1.dist-info/RECORD
